fluent_pipelines/__init__.py
fluent_pipelines/pipe.py
fluentpipelines-0.1.1.dist-info/METADATA
fluentpipelines-0.1.1.dist-info/WHEEL
fluentpipelines-0.1.1.dist-info/top_level.txt
fluentpipelines-0.1.1.dist-info/RECORD
