Metadata-Version: 2.1
Name: fluentpipelines
Version: 0.1.1
Summary: A Python package for building fluent pipelines
Home-page: https://github.com/JarriqTheTechie/fluentpipelines
Author: Jarriq Rolle
Author-email: jrolle@bnbbahamas.com
Classifier: Programming Language :: Python :: 3
Classifier: License :: OSI Approved :: MIT License
Classifier: Operating System :: OS Independent
Requires-Python: >=3.9
